setup.py
Labrador.egg-info/PKG-INFO
Labrador.egg-info/SOURCES.txt
Labrador.egg-info/dependency_links.txt
Labrador.egg-info/requires.txt
Labrador.egg-info/top_level.txt
bin/lab
labrador/__init__.py
labrador/cache/__init__.py
labrador/cache/yaml_cache.py
labrador/output/__init__.py
labrador/output/ini.py
labrador/output/properties.py
labrador/retriever/__init__.py
labrador/retriever/awsmeta.py
labrador/retriever/env.py
labrador/retriever/facter.py
labrador/retriever/file.py
labrador/retriever/http.py
labrador/retriever/iam.py
labrador/retriever/s3.py
labrador/retriever/string.py