Metadata-Version: 1.0
Name: Labrador
Version: 0.6.0
Summary: Configuration retrieval
Home-page: https://github.com/framed-data/labrador
Author: Elliot Block
Author-email: elliot@framed.io
License: UNKNOWN
Platform: UNKNOWN
